blazing_encoders-0.1.1.dist-info/METADATA
blazing_encoders-0.1.1.dist-info/WHEEL
blazing_encoders/__init__.py
blazing_encoders/blazing_encoders.cpython-310-x86_64-linux-gnu.so
blazing_encoders-0.1.1.dist-info/RECORD
