Metadata-Version: 2.1
Name: blazing_encoders
Version: 0.1.1
Author: Kirill Dubovikov <dubovikov.kirill@gmail.com>
Author-email: Kirill Dubovikov <dubovikov.kirill@gmail.com>
